recompy/FunkSVD.py
recompy/Initializer.py
recompy/Similarities.py
recompy/Test.py
recompy/__init__.py
recompy/data/movielens100k.csv
recompy/data/ratings_small.csv
recompy-1.0.3.dist-info/LICENSE
recompy-1.0.3.dist-info/METADATA
recompy-1.0.3.dist-info/WHEEL
recompy-1.0.3.dist-info/top_level.txt
recompy-1.0.3.dist-info/RECORD
