Metadata-Version: 2.1
Name: recompy
Version: 1.0.3
Summary: A recommender library
Home-page: https://github.com/canbul/recompy
Author: Can Bulguoglu, Oguz Kaplan, Onur Boyar, Emre Yuksel
Author-email: canbulguoglu@gmail.com
License: UNKNOWN
Platform: UNKNOWN
Classifier: Programming Language :: Python :: 3
Classifier: License :: OSI Approved :: MIT License
Classifier: Operating System :: OS Independent
Requires-Python: >=3.5
Requires-Dist: numpy (==1.18.4)
